{
  "tool_name": "Bash",
  "tool_input_preview": "{\"command\":\"cd /Users/davidandrews/PycharmProjects/lex-w157 && rtk git add packages/coding-agent/src/tools/fetch.ts && rtk git cherry-pick --continue --no-edit 2>&1\",\"description\":\"Stage resolved fetc...",
  "error": "Exit code 1\nok 3 files changed, 163 insertions(+), 29 deletions(-)\n[omc-team/upstream-parity-15-5-7/worker-15-5-7 4827429de] fix(tools): isolate read URL reader-mode fallback chain from remote stalls\n Author: roboomp <omp@can.ac>\n Date: Wed May 27 16:53:25 2026 +0000\n 3 files changed, 163 insertions(+), 29 deletions(-)\n create mode 100644 packages/coding-agent/test/tools/fetch-jina-stall.test.ts\nAuto-merging packages/coding-agent/src/edit/renderer.ts\nCONFLICT (content): Merge conflict in package...",
  "timestamp": "2026-05-27T20:11:22.016Z",
  "retry_count": 5
}